echohue/__init__.py
echohue/defaults.py
echohue/main.py
echohue-0.1.3.dist-info/licenses/LICENSE
echohue-0.1.3.dist-info/METADATA
echohue-0.1.3.dist-info/WHEEL
echohue-0.1.3.dist-info/top_level.txt
echohue-0.1.3.dist-info/RECORD
