Metadata-Version: 2.4
Name: echohue
Version: 0.1.3
Summary: Philips Hue lamp emulation for Amazon Echo
Home-page: https://github.com/mightytry/alexa-echo-hue
Author: mightytry
Author-email: 
License: MIT
Project-URL: Bug Tracker, https://github.com/mightytry/alexa-echo-hue/issues
Project-URL: Docs, https://github.com/mightytry/alexa-echo-hue
Project-URL: GitHub: repo, https://github.com/aio-libs/aiohttp
Project-URL: GitHub: issues, https://github.com/aio-libs/aiohttp/issues
Classifier: Programming Language :: Python :: 3
Classifier: License :: OSI Approved :: MIT License
Classifier: Operating System :: OS Independent
Requires-Python: >=3.11
License-File: LICENSE
Dynamic: license-file
